1/alu.v
module ALU(
    input wire signed [15:0] x0,y0,
    input wire zx,nx,zy,ny,f,no,
    output wire signed [15:0] out1,
    output wire zr,ng
);
    wire signed [15:0] x1, x2;
    wire signed [15:0] y1, y2;
    wire signed [15:0] out0;
    
    assign x1 = zx ? 16'sh0000 : x0; 
    assign x2 = nx ? ~x1 : x1;

    assign y1 = zy ? 16'sh0000 : y0;
    assign y2 = ny ? ~y1 : y1;    

    assign out0 = f? x2 + y2 : x2 & y2;
    assign out1 = no? ~out0: out0;

    assign zr = (out1 == 16'sh0000) ? 1 : 0;
    assign ng = (out1 < 0) ? 1 : 0;

    // assign
    // function nagate[15:0] (
    //     input wire signed [15:0] a,
    //     input bool
    // );
    // begin
    //     case (bool)
    //         0: nagate = a;
    //         1: nagate = ~a;
    //         default: zero = 0;
    //     endcase
    // end 
    // endfunction

    // function [15:0] zero(
    //     input wire signed [15:0] a,
    //     input bool
    // );
    // begin
    //     case (bool)
    //         0: zero = a;
    //         1: zero = 0;
    //         default: zero = 0;
    //     endcase
    // end 
    // endfunction

    // function [15:0] func(
    //     input wire signed [15:0] a,b,
    //     input f
    //     );
    // begin
    //     case (f)
    //         0: func = a + b;
    //         1: func = a & b;
    //         default: func = 16'sh0000;
    //     endcase
    // end 
    // endfunction
endmodule

1/alu_test.v
module ALUTEST;

reg signed [15:0] x,y;
reg zx,nx,zy,ny,f,no;
wire signed [15:0] out;
wire zr,ng;

ALU alu_instance(
        .x0(x),
        .y0(y),
        .zx(zx),
        .nx(nx),
        .zy(zy),
        .ny(ny),
        .f(f),
        .no(no),
        .out1(out),
        .zr(zr),
        .ng(ng)
    );

initial begin
    $dumpfile("alu_test.vcd");
    $dumpvars(1,ALUTEST);

    x = 16'sh0001; y = 16'sh0002;
    zx = 1; nx = 0; zy = 1; ny = 0; f = 1; no = 0;
    #10 
    zx = 1; nx = 1; zy = 1; ny = 1; f = 1; no = 1;
    #10
    zx = 1; nx = 1; zy = 1; ny = 0; f = 1; no = 0;
    #10
    zx = 0; nx = 0; zy = 1; ny = 1; f = 0; no = 0;
    #10
    zx = 1; nx = 1; zy = 0; ny = 0; f = 0; no = 0;
    #10
    zx = 0; nx = 0; zy = 1; ny = 1; f = 0; no = 1;
    #10
    zx = 1; nx = 1; zy = 0; ny = 0; f = 0; no = 1;
    #10
    zx = 0; nx = 0; zy = 1; ny = 1; f = 1; no = 1;
    #10
    zx = 1; nx = 1; zy = 0; ny = 0; f = 1; no = 1;
    #10
    zx = 0; nx = 1; zy = 1; ny = 1; f = 1; no = 1;
    #10
    zx = 1; nx = 1; zy = 0; ny = 1; f = 1; no = 1;
    #10
    zx = 0; nx = 0; zy = 1; ny = 1; f = 1; no = 0;
    #10
    zx = 1; nx = 1; zy = 0; ny = 0; f = 1; no = 0;
    #10
    zx = 0; nx = 0; zy = 0; ny = 0; f = 1; no = 0;
    #10
    zx = 0; nx = 1; zy = 0; ny = 0; f = 1; no = 1;
    #10
    zx = 0; nx = 0; zy = 0; ny = 1; f = 1; no = 1;
    #10
    zx = 0; nx = 0; zy = 0; ny = 0; f = 0; no = 0;
    #10
    zx = 0; nx = 1; zy = 0; ny = 1; f = 0; no = 1;
    #10
    $finish;
end

endmodule

1/alu_test.vcd
$date
	Sat Feb 11 11:38:51 2023
$end
$version
	Icarus Verilog
$end
$timescale
	1s
$end
$scope module ALUTEST $end
$var wire 1 ! zr $end
$var wire 16 " out [15:0] $end
$var wire 1 # ng $end
$var reg 1 $ f $end
$var reg 1 % no $end
$var reg 1 & nx $end
$var reg 1 ' ny $end
$var reg 16 ( x [15:0] $end
$var reg 16 ) y [15:0] $end
$var reg 1 * zx $end
$var reg 1 + zy $end
$upscope $end
$enddefinitions $end
#0
$dumpvars
1+
1*
b10 )
b1 (
0'
0&
0%
1$
0#
b0 "
1!
$end
#10
0!
0#
b1 "
1%
1'
1&
#20
1#
b1111111111111111 "
0%
0'
#30
0!
0#
b1 "
0$
1'
0&
0*
#40
b10 "
0'
0+
1&
1*
#50
1#
b1111111111111110 "
1%
1'
1+
0&
0*
#60
b1111111111111101 "
0'
0+
1&
1*
#70
1#
b1111111111111111 "
1$
1'
1+
0&
0*
#80
b1111111111111110 "
0'
0+
1&
1*
#90
0#
b10 "
1'
1+
0*
#100
b11 "
0+
1*
#110
1!
0#
b0 "
0%
1+
0&
0*
#120
0!
b1 "
0'
0+
1&
1*
#130
b11 "
0&
0*
#140
1#
b1111111111111111 "
1%
1&
#150
0#
b1 "
1'
0&
#160
1!
b0 "
0%
0$
0'
#170
0!
0#
b11 "
1%
1'
1&
